{
  "db_name": "PostgreSQL",
  "query": "SELECT id, password_hash, disabled\n           FROM auth.users\n           WHERE email = $1",
  "describe": {
    "columns": [
      {
        "ordinal": 0,
        "name": "id",
        "type_info": "Uuid"
      },
      {
        "ordinal": 1,
        "name": "password_hash",
        "type_info": "Text"
      },
      {
        "ordinal": 2,
        "name": "disabled",
        "type_info": "Bool"
      }
    ],
    "parameters": {
      "Left": [
        "Text"
      ]
    },
    "nullable": [
      false,
      false,
      false
    ]
  },
  "hash": "ac383c1eb471b9edbff93ee616f4ae5370b930b120718eadc989b6895ea5745d"
}
